[
  {
    "id": "001",
    "brand": "Lamborghini",
    "name": "Huracan",
    "price": "5000.00",
    "pic": "https://images.unsplash.com/photo-1544829099-13af78aa41b7?ixlib=rb-1.2.1&ixid=MXwxMjA3fDB8MHxleHBsb3",
    "info": "Highly performance car."
  },
  {
    "id": "002",
    "brand": "Nissan",
    "name": "GTR R35",
    "price": "5000.00",
    "pic": "https://images.unsplash.com/photo-1611859266238-4b98091d9d9b?ixid=MXwxMjA3fDB8MHxzZWFyY2h8MTB8fG5pc3",
    "info": "Nissan car"
  },
  {
    "id": "003",
    "brand": "Mazda",
    "name": "RX7",
    "price": "5000.00",
    "pic": "https://wallpaperaccess.com/full/412097.jpg",
    "info": "Mazda RX8"
  },
  {
    "id": "004",
    "brand": "Ferrari",
    "name": "SF90 Stradale",
    "price": "5000.00",
    "pic": "https://images.hdqwalls.com/download/ferrari-sf90-stradale-assetto-fiorano-2019-5k-gu-640x960.jpg",
    "info": "Ferrari"
  }
]
